{"Data": [{"Id": 589, "Pre": "Huyện", "Name": "Đông Hưng", "UnsignedLoweredName": null, "CityId": 54, "FullAddress": null, "Latitude": null, "Longitude": null, "Polygon": null, "ProductSellCount": 0, "ProductLeaseCount": 0, "Wards": [{"Id": 10139, "Pre": "Xã", "Name": "An Châu", "UnsignedLoweredName": null, "FullAddress": null, "DistrictId": 589, "CityId": null, "ProductSellCount": 0, "ProductLeaseCount": 0}, {"Id": 10159, "Pre": "Xã", "Name": "Bạch Đằng", "UnsignedLoweredName": null, "FullAddress": null, "DistrictId": 589, "CityId": null, "ProductSellCount": 0, "ProductLeaseCount": 0}, {"Id": 10142, "Pre": "Xã", "Name": "Chương Dương", "UnsignedLoweredName": null, "FullAddress": null, "DistrictId": 589, "CityId": null, "ProductSellCount": 0, "ProductLeaseCount": 0}, {"Id": 10117, "Pre": "Xã", "Name": "Đồng Phú", "UnsignedLoweredName": null, "FullAddress": null, "DistrictId": 589, "CityId": null, "ProductSellCount": 0, "ProductLeaseCount": 0}, {"Id": 10126, "Pre": "Xã", "Name": "Đô Lương", "UnsignedLoweredName": null, "FullAddress": null, "DistrictId": 589, "CityId": null, "ProductSellCount": 0, "ProductLeaseCount": 0}, {"Id": 10103, "Pre": "Xã", "Name": "Đông Á", "UnsignedLoweredName": null, "FullAddress": null, "DistrictId": 589, "CityId": null, "ProductSellCount": 0, "ProductLeaseCount": 0}, {"Id": 10085, "Pre": "Xã", "Name": "Đông Các", "UnsignedLoweredName": null, "FullAddress": null, "DistrictId": 589, "CityId": null, "ProductSellCount": 0, "ProductLeaseCount": 0}, {"Id": 10074, "Pre": "Xã", "Name": "Đông Cường", "UnsignedLoweredName": null, "FullAddress": null, "DistrictId": 589, "CityId": null, "ProductSellCount": 0, "ProductLeaseCount": 0}, {"Id": 10111, "Pre": "Xã", "Name": "Đông Dương", "UnsignedLoweredName": null, "FullAddress": null, "DistrictId": 589, "CityId": null, "ProductSellCount": 0, "ProductLeaseCount": 0}, {"Id": 10089, "Pre": "Xã", "Name": "Đông Động", "UnsignedLoweredName": null, "FullAddress": null, "DistrictId": 589, "CityId": null, "ProductSellCount": 0, "ProductLeaseCount": 0}, {"Id": 10083, "Pre": "Xã", "Name": "Đông Giang", "UnsignedLoweredName": null, "FullAddress": null, "DistrictId": 589, "CityId": null, "ProductSellCount": 0, "ProductLeaseCount": 0}, {"Id": 10084, "Pre": "Xã", "Name": "Đông Hà", "UnsignedLoweredName": null, "FullAddress": null, "DistrictId": 589, "CityId": null, "ProductSellCount": 0, "ProductLeaseCount": 0}, {"Id": 10106, "Pre": "Xã", "Name": "Đông Hoàng", "UnsignedLoweredName": null, "FullAddress": null, "DistrictId": 589, "CityId": null, "ProductSellCount": 0, "ProductLeaseCount": 0}, {"Id": 10087, "Pre": "Xã", "Name": "Đông Hợp", "UnsignedLoweredName": null, "FullAddress": null, "DistrictId": 589, "CityId": null, "ProductSellCount": 0, "ProductLeaseCount": 0}, {"Id": 10101, "Pre": "Xã", "Name": "Đông Huy", "UnsignedLoweredName": null, "FullAddress": null, "DistrictId": 589, "CityId": null, "ProductSellCount": 0, "ProductLeaseCount": 0}, {"Id": 10081, "Pre": "Xã", "Name": "Đông Kinh", "UnsignedLoweredName": null, "FullAddress": null, "DistrictId": 589, "CityId": null, "ProductSellCount": 0, "ProductLeaseCount": 0}, {"Id": 10080, "Pre": "Xã", "Name": "Đông La", "UnsignedLoweredName": null, "FullAddress": null, "DistrictId": 589, "CityId": null, "ProductSellCount": 0, "ProductLeaseCount": 0}, {"Id": 10096, "Pre": "Xã", "Name": "Đông Lĩnh", "UnsignedLoweredName": null, "FullAddress": null, "DistrictId": 589, "CityId": null, "ProductSellCount": 0, "ProductLeaseCount": 0}, {"Id": 10098, "Pre": "Xã", "Name": "Đông Phong", "UnsignedLoweredName": null, "FullAddress": null, "DistrictId": 589, "CityId": null, "ProductSellCount": 0, "ProductLeaseCount": 0}, {"Id": 10077, "Pre": "Xã", "Name": "Đông Phương", "UnsignedLoweredName": null, "FullAddress": null, "DistrictId": 589, "CityId": null, "ProductSellCount": 0, "ProductLeaseCount": 0}, {"Id": 10112, "Pre": "Xã", "Name": "Đông Quang", "UnsignedLoweredName": null, "FullAddress": null, "DistrictId": 589, "CityId": null, "ProductSellCount": 0, "ProductLeaseCount": 0}, {"Id": 10078, "Pre": "Xã", "Name": "Đông Sơn", "UnsignedLoweredName": null, "FullAddress": null, "DistrictId": 589, "CityId": null, "ProductSellCount": 0, "ProductLeaseCount": 0}, {"Id": 10093, "Pre": "Xã", "Name": "Đông Tân", "UnsignedLoweredName": null, "FullAddress": null, "DistrictId": 589, "CityId": null, "ProductSellCount": 0, "ProductLeaseCount": 0}, {"Id": 10091, "Pre": "Xã", "Name": "Đông Vinh", "UnsignedLoweredName": null, "FullAddress": null, "DistrictId": 589, "CityId": null, "ProductSellCount": 0, "ProductLeaseCount": 0}, {"Id": 10076, "Pre": "Xã", "Name": "Đông Xá", "UnsignedLoweredName": null, "FullAddress": null, "DistrictId": 589, "CityId": null, "ProductSellCount": 0, "ProductLeaseCount": 0}, {"Id": 10108, "Pre": "Xã", "Name": "Đông Xuân", "UnsignedLoweredName": null, "FullAddress": null, "DistrictId": 589, "CityId": null, "ProductSellCount": 0, "ProductLeaseCount": 0}, {"Id": 10147, "Pre": "Xã", "Name": "Hoa Lư", "UnsignedLoweredName": null, "FullAddress": null, "DistrictId": 589, "CityId": null, "ProductSellCount": 0, "ProductLeaseCount": 0}, {"Id": 10148, "Pre": "Xã", "Name": "Hoa Nam", "UnsignedLoweredName": null, "FullAddress": null, "DistrictId": 589, "CityId": null, "ProductSellCount": 0, "ProductLeaseCount": 0}, {"Id": 10154, "Pre": "Xã", "Name": "Hồng Châu", "UnsignedLoweredName": null, "FullAddress": null, "DistrictId": 589, "CityId": null, "ProductSellCount": 0, "ProductLeaseCount": 0}, {"Id": 10156, "Pre": "Xã", "Name": "Hồng Giang", "UnsignedLoweredName": null, "FullAddress": null, "DistrictId": 589, "CityId": null, "ProductSellCount": 0, "ProductLeaseCount": 0}, {"Id": 10152, "Pre": "Xã", "Name": "Hồng Việt", "UnsignedLoweredName": null, "FullAddress": null, "DistrictId": 589, "CityId": null, "ProductSellCount": 0, "ProductLeaseCount": 0}, {"Id": 10140, "Pre": "Xã", "Name": "Hợp Tiến", "UnsignedLoweredName": null, "FullAddress": null, "DistrictId": 589, "CityId": null, "ProductSellCount": 0, "ProductLeaseCount": 0}, {"Id": 10124, "Pre": "Xã", "Name": "Liên Giang", "UnsignedLoweredName": null, "FullAddress": null, "DistrictId": 589, "CityId": null, "ProductSellCount": 0, "ProductLeaseCount": 0}, {"Id": 10146, "Pre": "Xã", "Name": "Lô Giang", "UnsignedLoweredName": null, "FullAddress": null, "DistrictId": 589, "CityId": null, "ProductSellCount": 0, "ProductLeaseCount": 0}, {"Id": 10141, "Pre": "Xã", "Name": "Mê Linh", "UnsignedLoweredName": null, "FullAddress": null, "DistrictId": 589, "CityId": null, "ProductSellCount": 0, "ProductLeaseCount": 0}, {"Id": 10137, "Pre": "Xã", "Name": "Minh Châu", "UnsignedLoweredName": null, "FullAddress": null, "DistrictId": 589, "CityId": null, "ProductSellCount": 0, "ProductLeaseCount": 0}, {"Id": 10150, "Pre": "Xã", "Name": "Minh Tân", "UnsignedLoweredName": null, "FullAddress": null, "DistrictId": 589, "CityId": null, "ProductSellCount": 0, "ProductLeaseCount": 0}, {"Id": 10130, "Pre": "Xã", "Name": "Nguyên Xá", "UnsignedLoweredName": null, "FullAddress": null, "DistrictId": 589, "CityId": null, "ProductSellCount": 0, "ProductLeaseCount": 0}, {"Id": 10132, "Pre": "Xã", "Name": "Phong Châu", "UnsignedLoweredName": null, "FullAddress": null, "DistrictId": 589, "CityId": null, "ProductSellCount": 0, "ProductLeaseCount": 0}, {"Id": 10135, "Pre": "Xã", "Name": "Phú Châu", "UnsignedLoweredName": null, "FullAddress": null, "DistrictId": 589, "CityId": null, "ProductSellCount": 0, "ProductLeaseCount": 0}, {"Id": 10128, "Pre": "Xã", "Name": "Phú Lương", "UnsignedLoweredName": null, "FullAddress": null, "DistrictId": 589, "CityId": null, "ProductSellCount": 0, "ProductLeaseCount": 0}, {"Id": 10144, "Pre": "Xã", "Name": "Thăng Long", "UnsignedLoweredName": null, "FullAddress": null, "DistrictId": 589, "CityId": null, "ProductSellCount": 0, "ProductLeaseCount": 0}, {"Id": 10114, "Pre": "Xã", "Name": "Trọng Quan", "UnsignedLoweredName": null, "FullAddress": null, "DistrictId": 589, "CityId": null, "ProductSellCount": 0, "ProductLeaseCount": 0}], "Streets": [{"Id": 18774, "Pre": "Đường", "Name": "10", "UnsignedLoweredName": null, "FullAddress": null, "DistrictId": 589, "CityId": null, "ProductSellCount": 0, "ProductLeaseCount": 0}, {"Id": 7533, "Pre": "Đường", "Name": "Đống Năm", "UnsignedLoweredName": null, "FullAddress": null, "DistrictId": 589, "CityId": null, "ProductSellCount": 0, "ProductLeaseCount": 0}, {"Id": 18775, "Pre": "Đường", "Name": "Quốc Lộ 10", "UnsignedLoweredName": null, "FullAddress": null, "DistrictId": 589, "CityId": null, "ProductSellCount": 0, "ProductLeaseCount": 0}, {"Id": 4315, "Pre": "Đường", "Name": "Tỉnh lộ 216", "UnsignedLoweredName": null, "FullAddress": null, "DistrictId": 589, "CityId": null, "ProductSellCount": 0, "ProductLeaseCount": 0}, {"Id": 18776, "Pre": "Đường", "Name": "Tỉnh lộ 39B", "UnsignedLoweredName": null, "FullAddress": null, "DistrictId": 589, "CityId": null, "ProductSellCount": 0, "ProductLeaseCount": 0}], "Area": null, "Population": null, "PopulationDensity": null, "ImagesJson": null, "Url": null}, {"Id": 590, "Pre": "Huyện", "Name": "Hưng Hà", "UnsignedLoweredName": null, "CityId": 54, "FullAddress": null, "Latitude": null, "Longitude": null, "Polygon": null, "ProductSellCount": 0, "ProductLeaseCount": 0, "Wards": [{"Id": 10234, "Pre": "Xã", "Name": "Bắc Sơn", "UnsignedLoweredName": null, "FullAddress": null, "DistrictId": 590, "CityId": null, "ProductSellCount": 0, "ProductLeaseCount": 0}, {"Id": 10205, "Pre": "Xã", "Name": "Canh Tân", "UnsignedLoweredName": null, "FullAddress": null, "DistrictId": 590, "CityId": null, "ProductSellCount": 0, "ProductLeaseCount": 0}, {"Id": 10211, "Pre": "Xã", "Name": "Cộng Hòa", "UnsignedLoweredName": null, "FullAddress": null, "DistrictId": 590, "CityId": null, "ProductSellCount": 0, "ProductLeaseCount": 0}, {"Id": 10178, "Pre": "Xã", "Name": "Chí Hòa", "UnsignedLoweredName": null, "FullAddress": null, "DistrictId": 590, "CityId": null, "ProductSellCount": 0, "ProductLeaseCount": 0}, {"Id": 10245, "Pre": "Xã", "Name": "Chi Lăng", "UnsignedLoweredName": null, "FullAddress": null, "DistrictId": 590, "CityId": null, "ProductSellCount": 0, "ProductLeaseCount": 0}, {"Id": 10200, "Pre": "Xã", "Name": "Dân Chủ", "UnsignedLoweredName": null, "FullAddress": null, "DistrictId": 590, "CityId": null, "ProductSellCount": 0, "ProductLeaseCount": 0}, {"Id": 10198, "Pre": "Xã", "Name": "Duyên Hải", "UnsignedLoweredName": null, "FullAddress": null, "DistrictId": 590, "CityId": null, "ProductSellCount": 0, "ProductLeaseCount": 0}, {"Id": 10202, "Pre": "Xã", "Name": "Điệp Nông", "UnsignedLoweredName": null, "FullAddress": null, "DistrictId": 590, "CityId": null, "ProductSellCount": 0, "ProductLeaseCount": 0}, {"Id": 10228, "Pre": "Xã", "Name": "Đoan Hùng", "UnsignedLoweredName": null, "FullAddress": null, "DistrictId": 590, "CityId": null, "ProductSellCount": 0, "ProductLeaseCount": 0}, {"Id": 10182, "Pre": "Xã", "Name": "Độc Lập", "UnsignedLoweredName": null, "FullAddress": null, "DistrictId": 590, "CityId": null, "ProductSellCount": 0, "ProductLeaseCount": 0}, {"Id": 10236, "Pre": "Xã", "Name": "Đông Đô", "UnsignedLoweredName": null, "FullAddress": null, "DistrictId": 590, "CityId": null, "ProductSellCount": 0, "ProductLeaseCount": 0}, {"Id": 10241, "Pre": "Xã", "Name": "Hòa Bình", "UnsignedLoweredName": null, "FullAddress": null, "DistrictId": 590, "CityId": null, "ProductSellCount": 0, "ProductLeaseCount": 0}, {"Id": 10214, "Pre": "Xã", "Name": "Hòa Tiến", "UnsignedLoweredName": null, "FullAddress": null, "DistrictId": 590, "CityId": null, "ProductSellCount": 0, "ProductLeaseCount": 0}, {"Id": 10196, "Pre": "Xã", "Name": "Hồng An", "UnsignedLoweredName": null, "FullAddress": null, "DistrictId": 590, "CityId": null, "ProductSellCount": 0, "ProductLeaseCount": 0}, {"Id": 10188, "Pre": "Xã", "Name": "Hồng Lĩnh", "UnsignedLoweredName": null, "FullAddress": null, "DistrictId": 590, "CityId": null, "ProductSellCount": 0, "ProductLeaseCount": 0}, {"Id": 10176, "Pre": "Xã", "Name": "Hồng Minh", "UnsignedLoweredName": null, "FullAddress": null, "DistrictId": 590, "CityId": null, "ProductSellCount": 0, "ProductLeaseCount": 0}, {"Id": 10225, "Pre": "Xã", "Name": "Hùng Dũng", "UnsignedLoweredName": null, "FullAddress": null, "DistrictId": 590, "CityId": null, "ProductSellCount": 0, "ProductLeaseCount": 0}, {"Id": 10191, "Pre": "Xã", "Name": "Kim Trung", "UnsignedLoweredName": null, "FullAddress": null, "DistrictId": 590, "CityId": null, "ProductSellCount": 0, "ProductLeaseCount": 0}, {"Id": 10221, "Pre": "Xã", "Name": "Liên Hiệp", "UnsignedLoweredName": null, "FullAddress": null, "DistrictId": 590, "CityId": null, "ProductSellCount": 0, "ProductLeaseCount": 0}, {"Id": 10181, "Pre": "Xã", "Name": "Minh Hòa", "UnsignedLoweredName": null, "FullAddress": null, "DistrictId": 590, "CityId": null, "ProductSellCount": 0, "ProductLeaseCount": 0}, {"Id": 10190, "Pre": "Xã", "Name": "Minh Khai", "UnsignedLoweredName": null, "FullAddress": null, "DistrictId": 590, "CityId": null, "ProductSellCount": 0, "ProductLeaseCount": 0}, {"Id": 10184, "Pre": "Xã", "Name": "Minh Tân", "UnsignedLoweredName": null, "FullAddress": null, "DistrictId": 590, "CityId": null, "ProductSellCount": 0, "ProductLeaseCount": 0}, {"Id": 10218, "Pre": "Xã", "Name": "Phúc Khánh", "UnsignedLoweredName": null, "FullAddress": null, "DistrictId": 590, "CityId": null, "ProductSellCount": 0, "ProductLeaseCount": 0}, {"Id": 10209, "Pre": "Xã", "Name": "Tân Hòa", "UnsignedLoweredName": null, "FullAddress": null, "DistrictId": 590, "CityId": null, "ProductSellCount": 0, "ProductLeaseCount": 0}, {"Id": 10207, "Pre": "Xã", "Name": "Tân Lễ", "UnsignedLoweredName": null, "FullAddress": null, "DistrictId": 590, "CityId": null, "ProductSellCount": 0, "ProductLeaseCount": 0}, {"Id": 10216, "Pre": "Xã", "Name": "Tân Tiến", "UnsignedLoweredName": null, "FullAddress": null, "DistrictId": 590, "CityId": null, "ProductSellCount": 0, "ProductLeaseCount": 0}, {"Id": 10238, "Pre": "Xã", "Name": "Tây Đô", "UnsignedLoweredName": null, "FullAddress": null, "DistrictId": 590, "CityId": null, "ProductSellCount": 0, "ProductLeaseCount": 0}, {"Id": 10223, "Pre": "Xã", "Name": "Tiến Đức", "UnsignedLoweredName": null, "FullAddress": null, "DistrictId": 590, "CityId": null, "ProductSellCount": 0, "ProductLeaseCount": 0}, {"Id": 10194, "Pre": "Xã", "Name": "Thái Hưng", "UnsignedLoweredName": null, "FullAddress": null, "DistrictId": 590, "CityId": null, "ProductSellCount": 0, "ProductLeaseCount": 0}, {"Id": 10193, "Pre": "Xã", "Name": "Thái Phương", "UnsignedLoweredName": null, "FullAddress": null, "DistrictId": 590, "CityId": null, "ProductSellCount": 0, "ProductLeaseCount": 0}, {"Id": 10169, "Pre": "Thị trấn", "Name": "Thị trấn Hưng Hà", "UnsignedLoweredName": null, "FullAddress": null, "DistrictId": 590, "CityId": null, "ProductSellCount": 0, "ProductLeaseCount": 0}, {"Id": 10172, "Pre": "Thị trấn", "Name": "Thị trấn Hưng Nhân", "UnsignedLoweredName": null, "FullAddress": null, "DistrictId": 590, "CityId": null, "ProductSellCount": 0, "ProductLeaseCount": 0}, {"Id": 10231, "Pre": "Xã", "Name": "Thống Nhất", "UnsignedLoweredName": null, "FullAddress": null, "DistrictId": 590, "CityId": null, "ProductSellCount": 0, "ProductLeaseCount": 0}, {"Id": 10233, "Pre": "Xã", "Name": "Văn Cẩm", "UnsignedLoweredName": null, "FullAddress": null, "DistrictId": 590, "CityId": null, "ProductSellCount": 0, "ProductLeaseCount": 0}, {"Id": 10186, "Pre": "Xã", "Name": "Văn Lang", "UnsignedLoweredName": null, "FullAddress": null, "DistrictId": 590, "CityId": null, "ProductSellCount": 0, "ProductLeaseCount": 0}], "Streets": [{"Id": 18777, "Pre": "Đường", "Name": "39", "UnsignedLoweredName": null, "FullAddress": null, "DistrictId": 590, "CityId": null, "ProductSellCount": 0, "ProductLeaseCount": 0}, {"Id": 7595, "Pre": "Đường", "Name": "Khu Đầu", "UnsignedLoweredName": null, "FullAddress": null, "DistrictId": 590, "CityId": null, "ProductSellCount": 0, "ProductLeaseCount": 0}, {"Id": 18778, "Pre": "Đường", "Name": "Tỉnh lộ 216", "UnsignedLoweredName": null, "FullAddress": null, "DistrictId": 590, "CityId": null, "ProductSellCount": 0, "ProductLeaseCount": 0}, {"Id": 4336, "Pre": "Đường", "Name": "Tỉnh lộ 224", "UnsignedLoweredName": null, "FullAddress": null, "DistrictId": 590, "CityId": null, "ProductSellCount": 0, "ProductLeaseCount": 0}, {"Id": 18779, "Pre": "Đường", "Name": "Tỉnh lộ 226", "UnsignedLoweredName": null, "FullAddress": null, "DistrictId": 590, "CityId": null, "ProductSellCount": 0, "ProductLeaseCount": 0}], "Area": null, "Population": null, "PopulationDensity": null, "ImagesJson": null, "Url": null}, {"Id": 591, "Pre": "Huyện", "Name": "Kiến Xương", "UnsignedLoweredName": null, "CityId": 54, "FullAddress": null, "Latitude": null, "Longitude": null, "Polygon": null, "ProductSellCount": 0, "ProductLeaseCount": 0, "Wards": [{"Id": 10291, "Pre": "Xã", "Name": "An Bình", "UnsignedLoweredName": null, "FullAddress": null, "DistrictId": 591, "CityId": null, "ProductSellCount": 0, "ProductLeaseCount": 0}, {"Id": 10262, "Pre": "Xã", "Name": "An Bồi", "UnsignedLoweredName": null, "FullAddress": null, "DistrictId": 591, "CityId": null, "ProductSellCount": 0, "ProductLeaseCount": 0}, {"Id": 10326, "Pre": "Xã", "Name": "Bình Định", "UnsignedLoweredName": null, "FullAddress": null, "DistrictId": 591, "CityId": null, "ProductSellCount": 0, "ProductLeaseCount": 0}, {"Id": 10266, "Pre": "Xã", "Name": "Bình Minh", "UnsignedLoweredName": null, "FullAddress": null, "DistrictId": 591, "CityId": null, "ProductSellCount": 0, "ProductLeaseCount": 0}, {"Id": 10307, "Pre": "Xã", "Name": "Bình Nguyên", "UnsignedLoweredName": null, "FullAddress": null, "DistrictId": 591, "CityId": null, "ProductSellCount": 0, "ProductLeaseCount": 0}, {"Id": 10324, "Pre": "Xã", "Name": "Bình Thanh", "UnsignedLoweredName": null, "FullAddress": null, "DistrictId": 591, "CityId": null, "ProductSellCount": 0, "ProductLeaseCount": 0}, {"Id": 10303, "Pre": "Xã", "Name": "Đình Phùng", "UnsignedLoweredName": null, "FullAddress": null, "DistrictId": 591, "CityId": null, "ProductSellCount": 0, "ProductLeaseCount": 0}, {"Id": 10269, "Pre": "Xã", "Name": "Hoà Bình", "UnsignedLoweredName": null, "FullAddress": null, "DistrictId": 591, "CityId": null, "ProductSellCount": 0, "ProductLeaseCount": 0}, {"Id": 10329, "Pre": "Xã", "Name": "Hồng Tiến", "UnsignedLoweredName": null, "FullAddress": null, "DistrictId": 591, "CityId": null, "ProductSellCount": 0, "ProductLeaseCount": 0}, {"Id": 10296, "Pre": "Xã", "Name": "Hồng Thái", "UnsignedLoweredName": null, "FullAddress": null, "DistrictId": 591, "CityId": null, "ProductSellCount": 0, "ProductLeaseCount": 0}, {"Id": 10298, "Pre": "Xã", "Name": "Lê Lợi", "UnsignedLoweredName": null, "FullAddress": null, "DistrictId": 591, "CityId": null, "ProductSellCount": 0, "ProductLeaseCount": 0}, {"Id": 10317, "Pre": "Xã", "Name": "Minh Hưng", "UnsignedLoweredName": null, "FullAddress": null, "DistrictId": 591, "CityId": null, "ProductSellCount": 0, "ProductLeaseCount": 0}, {"Id": 10319, "Pre": "Xã", "Name": "Minh Tân", "UnsignedLoweredName": null, "FullAddress": null, "DistrictId": 591, "CityId": null, "ProductSellCount": 0, "ProductLeaseCount": 0}, {"Id": 10322, "Pre": "Xã", "Name": "Nam Bình", "UnsignedLoweredName": null, "FullAddress": null, "DistrictId": 591, "CityId": null, "ProductSellCount": 0, "ProductLeaseCount": 0}, {"Id": 10300, "Pre": "Xã", "Name": "Nam Cao", "UnsignedLoweredName": null, "FullAddress": null, "DistrictId": 591, "CityId": null, "ProductSellCount": 0, "ProductLeaseCount": 0}, {"Id": 10270, "Pre": "Xã", "Name": "Quang Bình", "UnsignedLoweredName": null, "FullAddress": null, "DistrictId": 591, "CityId": null, "ProductSellCount": 0, "ProductLeaseCount": 0}, {"Id": 10315, "Pre": "Xã", "Name": "Quang Hưng", "UnsignedLoweredName": null, "FullAddress": null, "DistrictId": 591, "CityId": null, "ProductSellCount": 0, "ProductLeaseCount": 0}, {"Id": 10271, "Pre": "Xã", "Name": "Quang Lịch", "UnsignedLoweredName": null, "FullAddress": null, "DistrictId": 591, "CityId": null, "ProductSellCount": 0, "ProductLeaseCount": 0}, {"Id": 10265, "Pre": "Xã", "Name": "Quang Minh", "UnsignedLoweredName": null, "FullAddress": null, "DistrictId": 591, "CityId": null, "ProductSellCount": 0, "ProductLeaseCount": 0}, {"Id": 10264, "Pre": "Xã", "Name": "Quang Trung", "UnsignedLoweredName": null, "FullAddress": null, "DistrictId": 591, "CityId": null, "ProductSellCount": 0, "ProductLeaseCount": 0}, {"Id": 10310, "Pre": "Xã", "Name": "Quốc Tuấn", "UnsignedLoweredName": null, "FullAddress": null, "DistrictId": 591, "CityId": null, "ProductSellCount": 0, "ProductLeaseCount": 0}, {"Id": 10312, "Pre": "Xã", "Name": "Quyết Tiến", "UnsignedLoweredName": null, "FullAddress": null, "DistrictId": 591, "CityId": null, "ProductSellCount": 0, "ProductLeaseCount": 0}, {"Id": 10258, "Pre": "Thị trấn", "Name": "Thanh Nê", "UnsignedLoweredName": null, "FullAddress": null, "DistrictId": 591, "CityId": null, "ProductSellCount": 0, "ProductLeaseCount": 0}, {"Id": 10304, "Pre": "Xã", "Name": "Thanh Tân", "UnsignedLoweredName": null, "FullAddress": null, "DistrictId": 591, "CityId": null, "ProductSellCount": 0, "ProductLeaseCount": 0}, {"Id": 10268, "Pre": "Xã", "Name": "Thượng Hiền", "UnsignedLoweredName": null, "FullAddress": null, "DistrictId": 591, "CityId": null, "ProductSellCount": 0, "ProductLeaseCount": 0}, {"Id": 10294, "Pre": "Xã", "Name": "Trà Giang", "UnsignedLoweredName": null, "FullAddress": null, "DistrictId": 591, "CityId": null, "ProductSellCount": 0, "ProductLeaseCount": 0}, {"Id": 10283, "Pre": "Xã", "Name": "Vũ An", "UnsignedLoweredName": null, "FullAddress": null, "DistrictId": 591, "CityId": null, "ProductSellCount": 0, "ProductLeaseCount": 0}, {"Id": 10278, "Pre": "Xã", "Name": "Vũ Bình", "UnsignedLoweredName": null, "FullAddress": null, "DistrictId": 591, "CityId": null, "ProductSellCount": 0, "ProductLeaseCount": 0}, {"Id": 10275, "Pre": "Xã", "Name": "Vũ Công", "UnsignedLoweredName": null, "FullAddress": null, "DistrictId": 591, "CityId": null, "ProductSellCount": 0, "ProductLeaseCount": 0}, {"Id": 10281, "Pre": "Xã", "Name": "Vũ Hoà", "UnsignedLoweredName": null, "FullAddress": null, "DistrictId": 591, "CityId": null, "ProductSellCount": 0, "ProductLeaseCount": 0}, {"Id": 12236, "Pre": "Xã", "Name": "Vũ Lạc", "UnsignedLoweredName": null, "FullAddress": null, "DistrictId": 591, "CityId": null, "ProductSellCount": 0, "ProductLeaseCount": 0}, {"Id": 10285, "Pre": "Xã", "Name": "Vũ Lễ", "UnsignedLoweredName": null, "FullAddress": null, "DistrictId": 591, "CityId": null, "ProductSellCount": 0, "ProductLeaseCount": 0}, {"Id": 10282, "Pre": "Xã", "Name": "Vũ Ninh", "UnsignedLoweredName": null, "FullAddress": null, "DistrictId": 591, "CityId": null, "ProductSellCount": 0, "ProductLeaseCount": 0}, {"Id": 10274, "Pre": "Xã", "Name": "Vũ Quý", "UnsignedLoweredName": null, "FullAddress": null, "DistrictId": 591, "CityId": null, "ProductSellCount": 0, "ProductLeaseCount": 0}, {"Id": 10288, "Pre": "Xã", "Name": "Vũ Sơn", "UnsignedLoweredName": null, "FullAddress": null, "DistrictId": 591, "CityId": null, "ProductSellCount": 0, "ProductLeaseCount": 0}, {"Id": 10287, "Pre": "Xã", "Name": "Vũ Tây", "UnsignedLoweredName": null, "FullAddress": null, "DistrictId": 591, "CityId": null, "ProductSellCount": 0, "ProductLeaseCount": 0}, {"Id": 10279, "Pre": "Xã", "Name": "Vũ Thắng", "UnsignedLoweredName": null, "FullAddress": null, "DistrictId": 591, "CityId": null, "ProductSellCount": 0, "ProductLeaseCount": 0}, {"Id": 10273, "Pre": "Xã", "Name": "Vũ Trung", "UnsignedLoweredName": null, "FullAddress": null, "DistrictId": 591, "CityId": null, "ProductSellCount": 0, "ProductLeaseCount": 0}], "Streets": [{"Id": 4318, "Pre": "Đường", "Name": "Tỉnh lộ 222", "UnsignedLoweredName": null, "FullAddress": null, "DistrictId": 591, "CityId": null, "ProductSellCount": 0, "ProductLeaseCount": 0}, {"Id": 4319, "Pre": "Đường", "Name": "Tỉnh lộ 223", "UnsignedLoweredName": null, "FullAddress": null, "DistrictId": 591, "CityId": null, "ProductSellCount": 0, "ProductLeaseCount": 0}, {"Id": 18780, "Pre": "Đường", "Name": "Tỉnh lộ 39B", "UnsignedLoweredName": null, "FullAddress": null, "DistrictId": 591, "CityId": null, "ProductSellCount": 0, "ProductLeaseCount": 0}], "Area": null, "Population": null, "PopulationDensity": null, "ImagesJson": null, "Url": null}, {"Id": 592, "Pre": "Huyện", "Name": "Quỳnh Phụ", "UnsignedLoweredName": null, "CityId": 54, "FullAddress": null, "Latitude": null, "Longitude": null, "Polygon": null, "ProductSellCount": 0, "ProductLeaseCount": 0, "Wards": [{"Id": 10413, "Pre": "Xã", "Name": "An Ấp", "UnsignedLoweredName": null, "FullAddress": null, "DistrictId": 592, "CityId": null, "ProductSellCount": 0, "ProductLeaseCount": 0}, {"Id": 10349, "Pre": "Thị trấn", "Name": "An Bài", "UnsignedLoweredName": null, "FullAddress": null, "DistrictId": 592, "CityId": null, "ProductSellCount": 0, "ProductLeaseCount": 0}, {"Id": 10414, "Pre": "Xã", "Name": "An Cầu", "UnsignedLoweredName": null, "FullAddress": null, "DistrictId": 592, "CityId": null, "ProductSellCount": 0, "ProductLeaseCount": 0}, {"Id": 10399, "Pre": "Xã", "Name": "An Dục", "UnsignedLoweredName": null, "FullAddress": null, "DistrictId": 592, "CityId": null, "ProductSellCount": 0, "ProductLeaseCount": 0}, {"Id": 10422, "Pre": "Xã", "Name": "An Đồng", "UnsignedLoweredName": null, "FullAddress": null, "DistrictId": 592, "CityId": null, "ProductSellCount": 0, "ProductLeaseCount": 0}, {"Id": 10419, "Pre": "Xã", "Name": "An Hiệp", "UnsignedLoweredName": null, "FullAddress": null, "DistrictId": 592, "CityId": null, "ProductSellCount": 0, "ProductLeaseCount": 0}, {"Id": 10424, "Pre": "Xã", "Name": "An Khê", "UnsignedLoweredName": null, "FullAddress": null, "DistrictId": 592, "CityId": null, "ProductSellCount": 0, "ProductLeaseCount": 0}, {"Id": 10397, "Pre": "Xã", "Name": "An Lễ", "UnsignedLoweredName": null, "FullAddress": null, "DistrictId": 592, "CityId": null, "ProductSellCount": 0, "ProductLeaseCount": 0}, {"Id": 10403, "Pre": "Xã", "Name": "An Mỹ", "UnsignedLoweredName": null, "FullAddress": null, "DistrictId": 592, "CityId": null, "ProductSellCount": 0, "ProductLeaseCount": 0}, {"Id": 10408, "Pre": "Xã", "Name": "An Ninh", "UnsignedLoweredName": null, "FullAddress": null, "DistrictId": 592, "CityId": null, "ProductSellCount": 0, "ProductLeaseCount": 0}, {"Id": 10410, "Pre": "Xã", "Name": "An Quý", "UnsignedLoweredName": null, "FullAddress": null, "DistrictId": 592, "CityId": null, "ProductSellCount": 0, "ProductLeaseCount": 0}, {"Id": 10417, "Pre": "Xã", "Name": "An Thái", "UnsignedLoweredName": null, "FullAddress": null, "DistrictId": 592, "CityId": null, "ProductSellCount": 0, "ProductLeaseCount": 0}, {"Id": 10406, "Pre": "Xã", "Name": "An Thanh", "UnsignedLoweredName": null, "FullAddress": null, "DistrictId": 592, "CityId": null, "ProductSellCount": 0, "ProductLeaseCount": 0}, {"Id": 10401, "Pre": "Xã", "Name": "An Tràng", "UnsignedLoweredName": null, "FullAddress": null, "DistrictId": 592, "CityId": null, "ProductSellCount": 0, "ProductLeaseCount": 0}, {"Id": 10396, "Pre": "Xã", "Name": "An Vinh", "UnsignedLoweredName": null, "FullAddress": null, "DistrictId": 592, "CityId": null, "ProductSellCount": 0, "ProductLeaseCount": 0}, {"Id": 10398, "Pre": "Xã", "Name": "An Vũ", "UnsignedLoweredName": null, "FullAddress": null, "DistrictId": 592, "CityId": null, "ProductSellCount": 0, "ProductLeaseCount": 0}, {"Id": 10395, "Pre": "Xã", "Name": "Đồng Tiến", "UnsignedLoweredName": null, "FullAddress": null, "DistrictId": 592, "CityId": null, "ProductSellCount": 0, "ProductLeaseCount": 0}, {"Id": 10394, "Pre": "Xã", "Name": "Đông Hải", "UnsignedLoweredName": null, "FullAddress": null, "DistrictId": 592, "CityId": null, "ProductSellCount": 0, "ProductLeaseCount": 0}, {"Id": 10364, "Pre": "Xã", "Name": "Quỳnh Bảo", "UnsignedLoweredName": null, "FullAddress": null, "DistrictId": 592, "CityId": null, "ProductSellCount": 0, "ProductLeaseCount": 0}, {"Id": 10347, "Pre": "Thị trấn", "Name": "Quỳnh Côi", "UnsignedLoweredName": null, "FullAddress": null, "DistrictId": 592, "CityId": null, "ProductSellCount": 0, "ProductLeaseCount": 0}, {"Id": 10359, "Pre": "Xã", "Name": "Quỳnh Châu", "UnsignedLoweredName": null, "FullAddress": null, "DistrictId": 592, "CityId": null, "ProductSellCount": 0, "ProductLeaseCount": 0}, {"Id": 10371, "Pre": "Xã", "Name": "Quỳnh Giao", "UnsignedLoweredName": null, "FullAddress": null, "DistrictId": 592, "CityId": null, "ProductSellCount": 0, "ProductLeaseCount": 0}, {"Id": 10382, "Pre": "Xã", "Name": "Quỳnh Hải", "UnsignedLoweredName": null, "FullAddress": null, "DistrictId": 592, "CityId": null, "ProductSellCount": 0, "ProductLeaseCount": 0}, {"Id": 10374, "Pre": "Xã", "Name": "Quỳnh Hoa", "UnsignedLoweredName": null, "FullAddress": null, "DistrictId": 592, "CityId": null, "ProductSellCount": 0, "ProductLeaseCount": 0}, {"Id": 10354, "Pre": "Xã", "Name": "Quỳnh Hoàng", "UnsignedLoweredName": null, "FullAddress": null, "DistrictId": 592, "CityId": null, "ProductSellCount": 0, "ProductLeaseCount": 0}, {"Id": 10385, "Pre": "Xã", "Name": "Quỳnh Hội", "UnsignedLoweredName": null, "FullAddress": null, "DistrictId": 592, "CityId": null, "ProductSellCount": 0, "ProductLeaseCount": 0}, {"Id": 10368, "Pre": "Xã", "Name": "Quỳnh Hồng", "UnsignedLoweredName": null, "FullAddress": null, "DistrictId": 592, "CityId": null, "ProductSellCount": 0, "ProductLeaseCount": 0}, {"Id": 10387, "Pre": "Xã", "Name": "Quỳnh Hưng", "UnsignedLoweredName": null, "FullAddress": null, "DistrictId": 592, "CityId": null, "ProductSellCount": 0, "ProductLeaseCount": 0}, {"Id": 10355, "Pre": "Xã", "Name": "Quỳnh Khê", "UnsignedLoweredName": null, "FullAddress": null, "DistrictId": 592, "CityId": null, "ProductSellCount": 0, "ProductLeaseCount": 0}, {"Id": 10351, "Pre": "Xã", "Name": "Quỳnh Lâm", "UnsignedLoweredName": null, "FullAddress": null, "DistrictId": 592, "CityId": null, "ProductSellCount": 0, "ProductLeaseCount": 0}, {"Id": 10379, "Pre": "Xã", "Name": "Quỳnh Minh", "UnsignedLoweredName": null, "FullAddress": null, "DistrictId": 592, "CityId": null, "ProductSellCount": 0, "ProductLeaseCount": 0}, {"Id": 10366, "Pre": "Xã", "Name": "Quỳnh Mỹ", "UnsignedLoweredName": null, "FullAddress": null, "DistrictId": 592, "CityId": null, "ProductSellCount": 0, "ProductLeaseCount": 0}, {"Id": 10352, "Pre": "Xã", "Name": "Quỳnh Ngọc", "UnsignedLoweredName": null, "FullAddress": null, "DistrictId": 592, "CityId": null, "ProductSellCount": 0, "ProductLeaseCount": 0}, {"Id": 10361, "Pre": "Xã", "Name": "Quỳnh Nguyên", "UnsignedLoweredName": null, "FullAddress": null, "DistrictId": 592, "CityId": null, "ProductSellCount": 0, "ProductLeaseCount": 0}, {"Id": 10357, "Pre": "Xã", "Name": "Quỳnh Sơn", "UnsignedLoweredName": null, "FullAddress": null, "DistrictId": 592, "CityId": null, "ProductSellCount": 0, "ProductLeaseCount": 0}, {"Id": 10376, "Pre": "Xã", "Name": "Quỳnh Thọ", "UnsignedLoweredName": null, "FullAddress": null, "DistrictId": 592, "CityId": null, "ProductSellCount": 0, "ProductLeaseCount": 0}, {"Id": 10392, "Pre": "Xã", "Name": "Quỳnh Trang", "UnsignedLoweredName": null, "FullAddress": null, "DistrictId": 592, "CityId": null, "ProductSellCount": 0, "ProductLeaseCount": 0}, {"Id": 10389, "Pre": "Xã", "Name": "Quỳnh Xá", "UnsignedLoweredName": null, "FullAddress": null, "DistrictId": 592, "CityId": null, "ProductSellCount": 0, "ProductLeaseCount": 0}], "Streets": [{"Id": 18781, "Pre": "Đường", "Name": "10", "UnsignedLoweredName": null, "FullAddress": null, "DistrictId": 592, "CityId": null, "ProductSellCount": 0, "ProductLeaseCount": 0}, {"Id": 18782, "Pre": "Đường", "Name": "Quốc Lộ 10", "UnsignedLoweredName": null, "FullAddress": null, "DistrictId": 592, "CityId": null, "ProductSellCount": 0, "ProductLeaseCount": 0}, {"Id": 18783, "Pre": "Đường", "Name": "Tỉnh lộ 216", "UnsignedLoweredName": null, "FullAddress": null, "DistrictId": 592, "CityId": null, "ProductSellCount": 0, "ProductLeaseCount": 0}, {"Id": 18784, "Pre": "Đường", "Name": "Tỉnh lộ 217", "UnsignedLoweredName": null, "FullAddress": null, "DistrictId": 592, "CityId": null, "ProductSellCount": 0, "ProductLeaseCount": 0}, {"Id": 18785, "Pre": "Đường", "Name": "Tỉnh lộ 224", "UnsignedLoweredName": null, "FullAddress": null, "DistrictId": 592, "CityId": null, "ProductSellCount": 0, "ProductLeaseCount": 0}], "Area": null, "Population": null, "PopulationDensity": null, "ImagesJson": null, "Url": null}, {"Id": 594, "Pre": "Huyện", "Name": "Tiền Hải", "UnsignedLoweredName": null, "CityId": 54, "FullAddress": null, "Latitude": null, "Longitude": null, "Polygon": null, "ProductSellCount": 0, "ProductLeaseCount": 0, "Wards": [{"Id": 10605, "Pre": "Xã", "Name": "An Ninh", "UnsignedLoweredName": null, "FullAddress": null, "DistrictId": 594, "CityId": null, "ProductSellCount": 0, "ProductLeaseCount": 0}, {"Id": 10606, "Pre": "Xã", "Name": "Bắc Hải", "UnsignedLoweredName": null, "FullAddress": null, "DistrictId": 594, "CityId": null, "ProductSellCount": 0, "ProductLeaseCount": 0}, {"Id": 10607, "Pre": "Xã", "Name": "Đông Cơ", "UnsignedLoweredName": null, "FullAddress": null, "DistrictId": 594, "CityId": null, "ProductSellCount": 0, "ProductLeaseCount": 0}, {"Id": 10608, "Pre": "Xã", "Name": "Đông Hải", "UnsignedLoweredName": null, "FullAddress": null, "DistrictId": 594, "CityId": null, "ProductSellCount": 0, "ProductLeaseCount": 0}, {"Id": 10611, "Pre": "Xã", "Name": "Đông Hoàng", "UnsignedLoweredName": null, "FullAddress": null, "DistrictId": 594, "CityId": null, "ProductSellCount": 0, "ProductLeaseCount": 0}, {"Id": 10612, "Pre": "Xã", "Name": "Đông Lâm", "UnsignedLoweredName": null, "FullAddress": null, "DistrictId": 594, "CityId": null, "ProductSellCount": 0, "ProductLeaseCount": 0}, {"Id": 10613, "Pre": "Xã", "Name": "Đông Long", "UnsignedLoweredName": null, "FullAddress": null, "DistrictId": 594, "CityId": null, "ProductSellCount": 0, "ProductLeaseCount": 0}, {"Id": 10614, "Pre": "Xã", "Name": "Đông Minh", "UnsignedLoweredName": null, "FullAddress": null, "DistrictId": 594, "CityId": null, "ProductSellCount": 0, "ProductLeaseCount": 0}, {"Id": 10621, "Pre": "Xã", "Name": "Đông Phong", "UnsignedLoweredName": null, "FullAddress": null, "DistrictId": 594, "CityId": null, "ProductSellCount": 0, "ProductLeaseCount": 0}, {"Id": 10623, "Pre": "Xã", "Name": "Đông Quý", "UnsignedLoweredName": null, "FullAddress": null, "DistrictId": 594, "CityId": null, "ProductSellCount": 0, "ProductLeaseCount": 0}, {"Id": 10624, "Pre": "Xã", "Name": "Đông Trà", "UnsignedLoweredName": null, "FullAddress": null, "DistrictId": 594, "CityId": null, "ProductSellCount": 0, "ProductLeaseCount": 0}, {"Id": 10626, "Pre": "Xã", "Name": "Đông Trung", "UnsignedLoweredName": null, "FullAddress": null, "DistrictId": 594, "CityId": null, "ProductSellCount": 0, "ProductLeaseCount": 0}, {"Id": 10627, "Pre": "Xã", "Name": "Đông Xuyên", "UnsignedLoweredName": null, "FullAddress": null, "DistrictId": 594, "CityId": null, "ProductSellCount": 0, "ProductLeaseCount": 0}, {"Id": 10630, "Pre": "Xã", "Name": "Nam Cường", "UnsignedLoweredName": null, "FullAddress": null, "DistrictId": 594, "CityId": null, "ProductSellCount": 0, "ProductLeaseCount": 0}, {"Id": 10628, "Pre": "Xã", "Name": "Nam Chính", "UnsignedLoweredName": null, "FullAddress": null, "DistrictId": 594, "CityId": null, "ProductSellCount": 0, "ProductLeaseCount": 0}, {"Id": 10632, "Pre": "Xã", "Name": "Nam Hà", "UnsignedLoweredName": null, "FullAddress": null, "DistrictId": 594, "CityId": null, "ProductSellCount": 0, "ProductLeaseCount": 0}, {"Id": 10633, "Pre": "Xã", "Name": "Nam Hải", "UnsignedLoweredName": null, "FullAddress": null, "DistrictId": 594, "CityId": null, "ProductSellCount": 0, "ProductLeaseCount": 0}, {"Id": 10634, "Pre": "Xã", "Name": "Nam Hồng", "UnsignedLoweredName": null, "FullAddress": null, "DistrictId": 594, "CityId": null, "ProductSellCount": 0, "ProductLeaseCount": 0}, {"Id": 10635, "Pre": "Xã", "Name": "Nam Hưng", "UnsignedLoweredName": null, "FullAddress": null, "DistrictId": 594, "CityId": null, "ProductSellCount": 0, "ProductLeaseCount": 0}, {"Id": 10661, "Pre": "Xã", "Name": "Nam Phú", "UnsignedLoweredName": null, "FullAddress": null, "DistrictId": 594, "CityId": null, "ProductSellCount": 0, "ProductLeaseCount": 0}, {"Id": 10655, "Pre": "Xã", "Name": "Nam Thắng", "UnsignedLoweredName": null, "FullAddress": null, "DistrictId": 594, "CityId": null, "ProductSellCount": 0, "ProductLeaseCount": 0}, {"Id": 10658, "Pre": "Xã", "Name": "Nam Thanh", "UnsignedLoweredName": null, "FullAddress": null, "DistrictId": 594, "CityId": null, "ProductSellCount": 0, "ProductLeaseCount": 0}, {"Id": 10615, "Pre": "Xã", "Name": "Nam Thịnh", "UnsignedLoweredName": null, "FullAddress": null, "DistrictId": 594, "CityId": null, "ProductSellCount": 0, "ProductLeaseCount": 0}, {"Id": 10617, "Pre": "Xã", "Name": "Nam Trung", "UnsignedLoweredName": null, "FullAddress": null, "DistrictId": 594, "CityId": null, "ProductSellCount": 0, "ProductLeaseCount": 0}, {"Id": 10618, "Pre": "Xã", "Name": "Phương Công", "UnsignedLoweredName": null, "FullAddress": null, "DistrictId": 594, "CityId": null, "ProductSellCount": 0, "ProductLeaseCount": 0}, {"Id": 10620, "Pre": "Xã", "Name": "Tây An", "UnsignedLoweredName": null, "FullAddress": null, "DistrictId": 594, "CityId": null, "ProductSellCount": 0, "ProductLeaseCount": 0}, {"Id": 10652, "Pre": "Xã", "Name": "Tây Giang", "UnsignedLoweredName": null, "FullAddress": null, "DistrictId": 594, "CityId": null, "ProductSellCount": 0, "ProductLeaseCount": 0}, {"Id": 10650, "Pre": "Xã", "Name": "Tây Lương", "UnsignedLoweredName": null, "FullAddress": null, "DistrictId": 594, "CityId": null, "ProductSellCount": 0, "ProductLeaseCount": 0}, {"Id": 10647, "Pre": "Xã", "Name": "Tây Ninh", "UnsignedLoweredName": null, "FullAddress": null, "DistrictId": 594, "CityId": null, "ProductSellCount": 0, "ProductLeaseCount": 0}, {"Id": 10644, "Pre": "Xã", "Name": "Tây Phong", "UnsignedLoweredName": null, "FullAddress": null, "DistrictId": 594, "CityId": null, "ProductSellCount": 0, "ProductLeaseCount": 0}, {"Id": 10642, "Pre": "Xã", "Name": "Tây Sơn", "UnsignedLoweredName": null, "FullAddress": null, "DistrictId": 594, "CityId": null, "ProductSellCount": 0, "ProductLeaseCount": 0}, {"Id": 10640, "Pre": "Xã", "Name": "Tây Tiến", "UnsignedLoweredName": null, "FullAddress": null, "DistrictId": 594, "CityId": null, "ProductSellCount": 0, "ProductLeaseCount": 0}, {"Id": 10603, "Pre": "Thị trấn", "Name": "Thị trấn Tiền Hải", "UnsignedLoweredName": null, "FullAddress": null, "DistrictId": 594, "CityId": null, "ProductSellCount": 0, "ProductLeaseCount": 0}, {"Id": 10637, "Pre": "Xã", "Name": "Vân Trường", "UnsignedLoweredName": null, "FullAddress": null, "DistrictId": 594, "CityId": null, "ProductSellCount": 0, "ProductLeaseCount": 0}, {"Id": 10636, "Pre": "Xã", "Name": "Vũ Lăng", "UnsignedLoweredName": null, "FullAddress": null, "DistrictId": 594, "CityId": null, "ProductSellCount": 0, "ProductLeaseCount": 0}], "Streets": [{"Id": 18850, "Pre": "Đường", "Name": "39", "UnsignedLoweredName": null, "FullAddress": null, "DistrictId": 594, "CityId": null, "ProductSellCount": 0, "ProductLeaseCount": 0}, {"Id": 18851, "Pre": "Đường", "Name": "Hùng Thắng", "UnsignedLoweredName": null, "FullAddress": null, "DistrictId": 594, "CityId": null, "ProductSellCount": 0, "ProductLeaseCount": 0}, {"Id": 4343, "Pre": "Đường", "Name": "Tỉnh lộ 219", "UnsignedLoweredName": null, "FullAddress": null, "DistrictId": 594, "CityId": null, "ProductSellCount": 0, "ProductLeaseCount": 0}, {"Id": 18852, "Pre": "Đường", "Name": "Tỉnh lộ 39B", "UnsignedLoweredName": null, "FullAddress": null, "DistrictId": 594, "CityId": null, "ProductSellCount": 0, "ProductLeaseCount": 0}], "Area": null, "Population": null, "PopulationDensity": null, "ImagesJson": null, "Url": null}, {"Id": 596, "Pre": "Thành phố", "Name": "Thái Bình", "UnsignedLoweredName": null, "CityId": 54, "FullAddress": null, "Latitude": null, "Longitude": null, "Polygon": null, "ProductSellCount": 0, "ProductLeaseCount": 0, "Wards": [{"Id": 10017, "Pre": "Phường", "Name": "Bồ Xuyên", "UnsignedLoweredName": null, "FullAddress": null, "DistrictId": 596, "CityId": null, "ProductSellCount": 0, "ProductLeaseCount": 0}, {"Id": 10032, "Pre": "Phường", "Name": "Đề Thám", "UnsignedLoweredName": null, "FullAddress": null, "DistrictId": 596, "CityId": null, "ProductSellCount": 0, "ProductLeaseCount": 0}, {"Id": 10036, "Pre": "Xã", "Name": "Đông Hòa", "UnsignedLoweredName": null, "FullAddress": null, "DistrictId": 596, "CityId": null, "ProductSellCount": 0, "ProductLeaseCount": 0}, {"Id": 10057, "Pre": "Xã", "Name": "Đông Mỹ", "UnsignedLoweredName": null, "FullAddress": null, "DistrictId": 596, "CityId": null, "ProductSellCount": 0, "ProductLeaseCount": 0}, {"Id": 10053, "Pre": "Xã", "Name": "Đông Thọ", "UnsignedLoweredName": null, "FullAddress": null, "DistrictId": 596, "CityId": null, "ProductSellCount": 0, "ProductLeaseCount": 0}, {"Id": 10034, "Pre": "Phường", "Name": "Hoàng Diệu", "UnsignedLoweredName": null, "FullAddress": null, "DistrictId": 596, "CityId": null, "ProductSellCount": 0, "ProductLeaseCount": 0}, {"Id": 10022, "Pre": "Phường", "Name": "Kỳ Bá", "UnsignedLoweredName": null, "FullAddress": null, "DistrictId": 596, "CityId": null, "ProductSellCount": 0, "ProductLeaseCount": 0}, {"Id": 10030, "Pre": "Phường", "Name": "Lê Hồng Phong", "UnsignedLoweredName": null, "FullAddress": null, "DistrictId": 596, "CityId": null, "ProductSellCount": 0, "ProductLeaseCount": 0}, {"Id": 10019, "Pre": "Phường", "Name": "Phú Khánh", "UnsignedLoweredName": null, "FullAddress": null, "DistrictId": 596, "CityId": null, "ProductSellCount": 0, "ProductLeaseCount": 0}, {"Id": 10043, "Pre": "Xã", "Name": "Phú Xuân", "UnsignedLoweredName": null, "FullAddress": null, "DistrictId": 596, "CityId": null, "ProductSellCount": 0, "ProductLeaseCount": 0}, {"Id": 10027, "Pre": "Phường", "Name": "Quang Trung", "UnsignedLoweredName": null, "FullAddress": null, "DistrictId": 596, "CityId": null, "ProductSellCount": 0, "ProductLeaseCount": 0}, {"Id": 10045, "Pre": "Xã", "Name": "Tân Bình", "UnsignedLoweredName": null, "FullAddress": null, "DistrictId": 596, "CityId": null, "ProductSellCount": 0, "ProductLeaseCount": 0}, {"Id": 10025, "Pre": "Phường", "Name": "Tiền Phong", "UnsignedLoweredName": null, "FullAddress": null, "DistrictId": 596, "CityId": null, "ProductSellCount": 0, "ProductLeaseCount": 0}, {"Id": 10033, "Pre": "Phường", "Name": "Trần Hưng Đạo", "UnsignedLoweredName": null, "FullAddress": null, "DistrictId": 596, "CityId": null, "ProductSellCount": 0, "ProductLeaseCount": 0}, {"Id": 10029, "Pre": "Phường", "Name": "Trần Lãm", "UnsignedLoweredName": null, "FullAddress": null, "DistrictId": 596, "CityId": null, "ProductSellCount": 0, "ProductLeaseCount": 0}, {"Id": 10038, "Pre": "Xã", "Name": "Vũ Chính", "UnsignedLoweredName": null, "FullAddress": null, "DistrictId": 596, "CityId": null, "ProductSellCount": 0, "ProductLeaseCount": 0}, {"Id": 10049, "Pre": "Xã", "Name": "Vũ Đông", "UnsignedLoweredName": null, "FullAddress": null, "DistrictId": 596, "CityId": null, "ProductSellCount": 0, "ProductLeaseCount": 0}, {"Id": 10051, "Pre": "Xã", "Name": "Vũ Lạc", "UnsignedLoweredName": null, "FullAddress": null, "DistrictId": 596, "CityId": null, "ProductSellCount": 0, "ProductLeaseCount": 0}, {"Id": 10039, "Pre": "Xã", "Name": "Vũ Phúc", "UnsignedLoweredName": null, "FullAddress": null, "DistrictId": 596, "CityId": null, "ProductSellCount": 0, "ProductLeaseCount": 0}], "Streets": [{"Id": 18786, "Pre": "Đường", "Name": "10", "UnsignedLoweredName": null, "FullAddress": null, "DistrictId": 596, "CityId": null, "ProductSellCount": 0, "ProductLeaseCount": 0}, {"Id": 20454, "Pre": "Đường", "Name": "Bồ Xuyên", "UnsignedLoweredName": null, "FullAddress": null, "DistrictId": 596, "CityId": null, "ProductSellCount": 0, "ProductLeaseCount": 0}, {"Id": 6124, "Pre": "Đường", "Name": "Bùi Sỹ Tiêm", "UnsignedLoweredName": null, "FullAddress": null, "DistrictId": 596, "CityId": null, "ProductSellCount": 0, "ProductLeaseCount": 0}, {"Id": 18787, "Pre": "Đường", "Name": "Chu Văn An", "UnsignedLoweredName": null, "FullAddress": null, "DistrictId": 596, "CityId": null, "ProductSellCount": 0, "ProductLeaseCount": 0}, {"Id": 7387, "Pre": "Đường", "Name": "Doãn Khuê", "UnsignedLoweredName": null, "FullAddress": null, "DistrictId": 596, "CityId": null, "ProductSellCount": 0, "ProductLeaseCount": 0}, {"Id": 18788, "Pre": "Đường", "Name": "Đặng Nghiêm", "UnsignedLoweredName": null, "FullAddress": null, "DistrictId": 596, "CityId": null, "ProductSellCount": 0, "ProductLeaseCount": 0}, {"Id": 8548, "Pre": "Đường", "Name": "Đê Vùng", "UnsignedLoweredName": null, "FullAddress": null, "DistrictId": 596, "CityId": null, "ProductSellCount": 0, "ProductLeaseCount": 0}, {"Id": 18789, "Pre": "Đường", "Name": "Đinh Tiên Hoàng", "UnsignedLoweredName": null, "FullAddress": null, "DistrictId": 596, "CityId": null, "ProductSellCount": 0, "ProductLeaseCount": 0}, {"Id": 6481, "Pre": "Đường", "Name": "Đỗ Lý Khiêm", "UnsignedLoweredName": null, "FullAddress": null, "DistrictId": 596, "CityId": null, "ProductSellCount": 0, "ProductLeaseCount": 0}, {"Id": 18790, "Pre": "Đường", "Name": "Đoàn Nguyễn Tuấn", "UnsignedLoweredName": null, "FullAddress": null, "DistrictId": 596, "CityId": null, "ProductSellCount": 0, "ProductLeaseCount": 0}, {"Id": 7157, "Pre": "Đường", "Name": "Đốc Đen", "UnsignedLoweredName": null, "FullAddress": null, "DistrictId": 596, "CityId": null, "ProductSellCount": 0, "ProductLeaseCount": 0}, {"Id": 6647, "Pre": "Đường", "Name": "Đốc Nhưỡng", "UnsignedLoweredName": null, "FullAddress": null, "DistrictId": 596, "CityId": null, "ProductSellCount": 0, "ProductLeaseCount": 0}, {"Id": 18791, "Pre": "Phố", "Name": "Hai Bà Trưng", "UnsignedLoweredName": null, "FullAddress": null, "DistrictId": 596, "CityId": null, "ProductSellCount": 0, "ProductLeaseCount": 0}, {"Id": 18792, "Pre": "Đường", "Name": "Hòa An 8", "UnsignedLoweredName": null, "FullAddress": null, "DistrictId": 596, "CityId": null, "ProductSellCount": 0, "ProductLeaseCount": 0}, {"Id": 18793, "Pre": "Đường", "Name": "Hoàng Công Chất", "UnsignedLoweredName": null, "FullAddress": null, "DistrictId": 596, "CityId": null, "ProductSellCount": 0, "ProductLeaseCount": 0}, {"Id": 18794, "Pre": "Đường", "Name": "Hoàng Diệu", "UnsignedLoweredName": null, "FullAddress": null, "DistrictId": 596, "CityId": null, "ProductSellCount": 0, "ProductLeaseCount": 0}, {"Id": 18795, "Pre": "Đường", "Name": "Hoàng Minh Thảo", "UnsignedLoweredName": null, "FullAddress": null, "DistrictId": 596, "CityId": null, "ProductSellCount": 0, "ProductLeaseCount": 0}, {"Id": 18796, "Pre": "Đường", "Name": "Hoàng Văn Thái", "UnsignedLoweredName": null, "FullAddress": null, "DistrictId": 596, "CityId": null, "ProductSellCount": 0, "ProductLeaseCount": 0}, {"Id": 22738, "Pre": "Đường", "Name": "Hoàng Văn Thụ", "UnsignedLoweredName": null, "FullAddress": null, "DistrictId": 596, "CityId": null, "ProductSellCount": 0, "ProductLeaseCount": 0}, {"Id": 18797, "Pre": "Đường", "Name": "Hùng Thắng", "UnsignedLoweredName": null, "FullAddress": null, "DistrictId": 596, "CityId": null, "ProductSellCount": 0, "ProductLeaseCount": 0}, {"Id": 18798, "Pre": "Đường", "Name": "Hùng Vương", "UnsignedLoweredName": null, "FullAddress": null, "DistrictId": 596, "CityId": null, "ProductSellCount": 0, "ProductLeaseCount": 0}, {"Id": 18799, "Pre": "Phố", "Name": "Kỳ Đồng", "UnsignedLoweredName": null, "FullAddress": null, "DistrictId": 596, "CityId": null, "ProductSellCount": 0, "ProductLeaseCount": 0}, {"Id": 18800, "Pre": "Đường", "Name": "Lê Đại Hành", "UnsignedLoweredName": null, "FullAddress": null, "DistrictId": 596, "CityId": null, "ProductSellCount": 0, "ProductLeaseCount": 0}, {"Id": 18801, "Pre": "Đường", "Name": "Lê Lợi", "UnsignedLoweredName": null, "FullAddress": null, "DistrictId": 596, "CityId": null, "ProductSellCount": 0, "ProductLeaseCount": 0}, {"Id": 18802, "Pre": "Đường", "Name": "Lê Quý Đôn", "UnsignedLoweredName": null, "FullAddress": null, "DistrictId": 596, "CityId": null, "ProductSellCount": 0, "ProductLeaseCount": 0}, {"Id": 18803, "Pre": "Đường", "Name": "Lê Thánh Tông", "UnsignedLoweredName": null, "FullAddress": null, "DistrictId": 596, "CityId": null, "ProductSellCount": 0, "ProductLeaseCount": 0}, {"Id": 18804, "Pre": "Đường", "Name": "Liên Xã", "UnsignedLoweredName": null, "FullAddress": null, "DistrictId": 596, "CityId": null, "ProductSellCount": 0, "ProductLeaseCount": 0}, {"Id": 18805, "Pre": "Đường", "Name": "Long Hưng", "UnsignedLoweredName": null, "FullAddress": null, "DistrictId": 596, "CityId": null, "ProductSellCount": 0, "ProductLeaseCount": 0}, {"Id": 18806, "Pre": "Đường", "Name": "Lý Bôn", "UnsignedLoweredName": null, "FullAddress": null, "DistrictId": 596, "CityId": null, "ProductSellCount": 0, "ProductLeaseCount": 0}, {"Id": 18807, "Pre": "Đường", "Name": "Lý Thái Tổ", "UnsignedLoweredName": null, "FullAddress": null, "DistrictId": 596, "CityId": null, "ProductSellCount": 0, "ProductLeaseCount": 0}, {"Id": 18808, "Pre": "Phố", "Name": "Lý Thường Kiệt", "UnsignedLoweredName": null, "FullAddress": null, "DistrictId": 596, "CityId": null, "ProductSellCount": 0, "ProductLeaseCount": 0}, {"Id": 18809, "Pre": "Đường", "Name": "Minh Khai", "UnsignedLoweredName": null, "FullAddress": null, "DistrictId": 596, "CityId": null, "ProductSellCount": 0, "ProductLeaseCount": 0}, {"Id": 8393, "Pre": "Đường", "Name": "Ngô Quang Bích", "UnsignedLoweredName": null, "FullAddress": null, "DistrictId": 596, "CityId": null, "ProductSellCount": 0, "ProductLeaseCount": 0}, {"Id": 18810, "Pre": "Đường", "Name": "Ngô Quyền", "UnsignedLoweredName": null, "FullAddress": null, "DistrictId": 596, "CityId": null, "ProductSellCount": 0, "ProductLeaseCount": 0}, {"Id": 18811, "Pre": "Đường", "Name": "Ngô Thì Nhậm", "UnsignedLoweredName": null, "FullAddress": null, "DistrictId": 596, "CityId": null, "ProductSellCount": 0, "ProductLeaseCount": 0}, {"Id": 18812, "Pre": "Đường", "Name": "Ngô Văn Sở", "UnsignedLoweredName": null, "FullAddress": null, "DistrictId": 596, "CityId": null, "ProductSellCount": 0, "ProductLeaseCount": 0}, {"Id": 18813, "Pre": "Đường", "Name": "Nguyễn Công Trứ", "UnsignedLoweredName": null, "FullAddress": null, "DistrictId": 596, "CityId": null, "ProductSellCount": 0, "ProductLeaseCount": 0}, {"Id": 18814, "Pre": "Đường", "Name": "Nguyễn Công Trung", "UnsignedLoweredName": null, "FullAddress": null, "DistrictId": 596, "CityId": null, "ProductSellCount": 0, "ProductLeaseCount": 0}, {"Id": 5674, "Pre": "Phố", "Name": "Nguyễn Danh Đới", "UnsignedLoweredName": null, "FullAddress": null, "DistrictId": 596, "CityId": null, "ProductSellCount": 0, "ProductLeaseCount": 0}, {"Id": 18815, "Pre": "Đường", "Name": "Nguyễn Đình Chính", "UnsignedLoweredName": null, "FullAddress": null, "DistrictId": 596, "CityId": null, "ProductSellCount": 0, "ProductLeaseCount": 0}, {"Id": 18816, "Pre": "Đường", "Name": "Nguyễn Ngọc Sanh", "UnsignedLoweredName": null, "FullAddress": null, "DistrictId": 596, "CityId": null, "ProductSellCount": 0, "ProductLeaseCount": 0}, {"Id": 5955, "Pre": "Đường", "Name": "Nguyễn Tông Quai", "UnsignedLoweredName": null, "FullAddress": null, "DistrictId": 596, "CityId": null, "ProductSellCount": 0, "ProductLeaseCount": 0}, {"Id": 18817, "Pre": "Đường", "Name": "Nguyễn Thái Học", "UnsignedLoweredName": null, "FullAddress": null, "DistrictId": 596, "CityId": null, "ProductSellCount": 0, "ProductLeaseCount": 0}, {"Id": 7388, "Pre": "Đường", "Name": "Nguyễn Thành", "UnsignedLoweredName": null, "FullAddress": null, "DistrictId": 596, "CityId": null, "ProductSellCount": 0, "ProductLeaseCount": 0}, {"Id": 18818, "Pre": "Đường", "Name": "Nguyễn Thị Minh Khai", "UnsignedLoweredName": null, "FullAddress": null, "DistrictId": 596, "CityId": null, "ProductSellCount": 0, "ProductLeaseCount": 0}, {"Id": 18819, "Pre": "Đường", "Name": "Nguyễn Trãi", "UnsignedLoweredName": null, "FullAddress": null, "DistrictId": 596, "CityId": null, "ProductSellCount": 0, "ProductLeaseCount": 0}, {"Id": 18820, "Pre": "Đường", "Name": "Nguyễn Văn Côn", "UnsignedLoweredName": null, "FullAddress": null, "DistrictId": 596, "CityId": null, "ProductSellCount": 0, "ProductLeaseCount": 0}, {"Id": 5954, "Pre": "Đường", "Name": "Nguyễn Văn Năng", "UnsignedLoweredName": null, "FullAddress": null, "DistrictId": 596, "CityId": null, "ProductSellCount": 0, "ProductLeaseCount": 0}, {"Id": 5863, "Pre": "Đường", "Name": "Phạm Huy Quang", "UnsignedLoweredName": null, "FullAddress": null, "DistrictId": 596, "CityId": null, "ProductSellCount": 0, "ProductLeaseCount": 0}, {"Id": 18821, "Pre": "Đường", "Name": "Phạm Ngũ Lão", "UnsignedLoweredName": null, "FullAddress": null, "DistrictId": 596, "CityId": null, "ProductSellCount": 0, "ProductLeaseCount": 0}, {"Id": 18822, "Pre": "Đường", "Name": "Phan Bá Vành", "UnsignedLoweredName": null, "FullAddress": null, "DistrictId": 596, "CityId": null, "ProductSellCount": 0, "ProductLeaseCount": 0}, {"Id": 18823, "Pre": "Đường", "Name": "Phan Bội Châu", "UnsignedLoweredName": null, "FullAddress": null, "DistrictId": 596, "CityId": null, "ProductSellCount": 0, "ProductLeaseCount": 0}, {"Id": 18824, "Pre": "Đường", "Name": "Phần Lăng 8", "UnsignedLoweredName": null, "FullAddress": null, "DistrictId": 596, "CityId": null, "ProductSellCount": 0, "ProductLeaseCount": 0}, {"Id": 18825, "Pre": "Đường", "Name": "Quách Đỉnh Bảo", "UnsignedLoweredName": null, "FullAddress": null, "DistrictId": 596, "CityId": null, "ProductSellCount": 0, "ProductLeaseCount": 0}, {"Id": 18826, "Pre": "Đường", "Name": "Quách Hữu Nghiêm", "UnsignedLoweredName": null, "FullAddress": null, "DistrictId": 596, "CityId": null, "ProductSellCount": 0, "ProductLeaseCount": 0}, {"Id": 18827, "Pre": "Đường", "Name": "Quang Trung", "UnsignedLoweredName": null, "FullAddress": null, "DistrictId": 596, "CityId": null, "ProductSellCount": 0, "ProductLeaseCount": 0}, {"Id": 18828, "Pre": "Đường", "Name": "Quốc Lộ 10", "UnsignedLoweredName": null, "FullAddress": null, "DistrictId": 596, "CityId": null, "ProductSellCount": 0, "ProductLeaseCount": 0}, {"Id": 18829, "Pre": "Đường", "Name": "Tân Thới Hiệp 1", "UnsignedLoweredName": null, "FullAddress": null, "DistrictId": 596, "CityId": null, "ProductSellCount": 0, "ProductLeaseCount": 0}, {"Id": 18830, "Pre": "Đường", "Name": "Tây Hào", "UnsignedLoweredName": null, "FullAddress": null, "DistrictId": 596, "CityId": null, "ProductSellCount": 0, "ProductLeaseCount": 0}, {"Id": 18831, "Pre": "Đường", "Name": "Tiền Hải", "UnsignedLoweredName": null, "FullAddress": null, "DistrictId": 596, "CityId": null, "ProductSellCount": 0, "ProductLeaseCount": 0}, {"Id": 18832, "Pre": "Đường", "Name": "Tỉnh lộ 39B", "UnsignedLoweredName": null, "FullAddress": null, "DistrictId": 596, "CityId": null, "ProductSellCount": 0, "ProductLeaseCount": 0}, {"Id": 18833, "Pre": "Đường", "Name": "Trần Bình Trọng", "UnsignedLoweredName": null, "FullAddress": null, "DistrictId": 596, "CityId": null, "ProductSellCount": 0, "ProductLeaseCount": 0}, {"Id": 18834, "Pre": "Đường", "Name": "Trần Hưng Đạo", "UnsignedLoweredName": null, "FullAddress": null, "DistrictId": 596, "CityId": null, "ProductSellCount": 0, "ProductLeaseCount": 0}, {"Id": 18835, "Pre": "Đường", "Name": "Trần Khánh Dư", "UnsignedLoweredName": null, "FullAddress": null, "DistrictId": 596, "CityId": null, "ProductSellCount": 0, "ProductLeaseCount": 0}, {"Id": 18836, "Pre": "Đường", "Name": "Trần Lãm", "UnsignedLoweredName": null, "FullAddress": null, "DistrictId": 596, "CityId": null, "ProductSellCount": 0, "ProductLeaseCount": 0}, {"Id": 18838, "Pre": "Đường", "Name": "Trần Nhật Duật", "UnsignedLoweredName": null, "FullAddress": null, "DistrictId": 596, "CityId": null, "ProductSellCount": 0, "ProductLeaseCount": 0}, {"Id": 18837, "Pre": "Đường", "Name": "Trần Nhân Tông", "UnsignedLoweredName": null, "FullAddress": null, "DistrictId": 596, "CityId": null, "ProductSellCount": 0, "ProductLeaseCount": 0}, {"Id": 18839, "Pre": "Đường", "Name": "Trần Quang Diệu", "UnsignedLoweredName": null, "FullAddress": null, "DistrictId": 596, "CityId": null, "ProductSellCount": 0, "ProductLeaseCount": 0}, {"Id": 18840, "Pre": "Đường", "Name": "Trần Quang Khải", "UnsignedLoweredName": null, "FullAddress": null, "DistrictId": 596, "CityId": null, "ProductSellCount": 0, "ProductLeaseCount": 0}, {"Id": 18841, "Pre": "Đường", "Name": "Trần Thái Tông", "UnsignedLoweredName": null, "FullAddress": null, "DistrictId": 596, "CityId": null, "ProductSellCount": 0, "ProductLeaseCount": 0}, {"Id": 18842, "Pre": "Đường", "Name": "Trần Thánh Tông", "UnsignedLoweredName": null, "FullAddress": null, "DistrictId": 596, "CityId": null, "ProductSellCount": 0, "ProductLeaseCount": 0}, {"Id": 9241, "Pre": "Đường", "Name": "Trần Thị Dung", "UnsignedLoweredName": null, "FullAddress": null, "DistrictId": 596, "CityId": null, "ProductSellCount": 0, "ProductLeaseCount": 0}, {"Id": 18843, "Pre": "Đường", "Name": "Trần Thủ Độ", "UnsignedLoweredName": null, "FullAddress": null, "DistrictId": 596, "CityId": null, "ProductSellCount": 0, "ProductLeaseCount": 0}, {"Id": 18844, "Pre": "Đường", "Name": "Trưng Trắc", "UnsignedLoweredName": null, "FullAddress": null, "DistrictId": 596, "CityId": null, "ProductSellCount": 0, "ProductLeaseCount": 0}, {"Id": 8532, "Pre": "Đường", "Name": "Vũ Trường", "UnsignedLoweredName": null, "FullAddress": null, "DistrictId": 596, "CityId": null, "ProductSellCount": 0, "ProductLeaseCount": 0}], "Area": null, "Population": null, "PopulationDensity": null, "ImagesJson": null, "Url": null}, {"Id": 593, "Pre": "Huyện", "Name": "Thái Thuỵ", "UnsignedLoweredName": null, "CityId": 54, "FullAddress": null, "Latitude": null, "Longitude": null, "Polygon": null, "ProductSellCount": 0, "ProductLeaseCount": 0, "Wards": [{"Id": 10471, "Pre": "Thị trấn", "Name": "Diêm Điền", "UnsignedLoweredName": null, "FullAddress": null, "DistrictId": 593, "CityId": null, "ProductSellCount": 0, "ProductLeaseCount": 0}, {"Id": 10525, "Pre": "Xã", "Name": "Hồng Quỳnh", "UnsignedLoweredName": null, "FullAddress": null, "DistrictId": 593, "CityId": null, "ProductSellCount": 0, "ProductLeaseCount": 0}, {"Id": 10566, "Pre": "Xã", "Name": "Mỹ Lộc", "UnsignedLoweredName": null, "FullAddress": null, "DistrictId": 593, "CityId": null, "ProductSellCount": 0, "ProductLeaseCount": 0}, {"Id": 10577, "Pre": "Xã", "Name": "Thái An", "UnsignedLoweredName": null, "FullAddress": null, "DistrictId": 593, "CityId": null, "ProductSellCount": 0, "ProductLeaseCount": 0}, {"Id": 10554, "Pre": "Xã", "Name": "Thái Dương", "UnsignedLoweredName": null, "FullAddress": null, "DistrictId": 593, "CityId": null, "ProductSellCount": 0, "ProductLeaseCount": 0}, {"Id": 10573, "Pre": "Xã", "Name": "Thái Đô", "UnsignedLoweredName": null, "FullAddress": null, "DistrictId": 593, "CityId": null, "ProductSellCount": 0, "ProductLeaseCount": 0}, {"Id": 10548, "Pre": "Xã", "Name": "Thái Giang", "UnsignedLoweredName": null, "FullAddress": null, "DistrictId": 593, "CityId": null, "ProductSellCount": 0, "ProductLeaseCount": 0}, {"Id": 10551, "Pre": "Xã", "Name": "Thái Hà", "UnsignedLoweredName": null, "FullAddress": null, "DistrictId": 593, "CityId": null, "ProductSellCount": 0, "ProductLeaseCount": 0}, {"Id": 10484, "Pre": "Xã", "Name": "Thái Hòa", "UnsignedLoweredName": null, "FullAddress": null, "DistrictId": 593, "CityId": null, "ProductSellCount": 0, "ProductLeaseCount": 0}, {"Id": 10562, "Pre": "Xã", "Name": "Thái Học", "UnsignedLoweredName": null, "FullAddress": null, "DistrictId": 593, "CityId": null, "ProductSellCount": 0, "ProductLeaseCount": 0}, {"Id": 10555, "Pre": "Xã", "Name": "Thái Hồng", "UnsignedLoweredName": null, "FullAddress": null, "DistrictId": 593, "CityId": null, "ProductSellCount": 0, "ProductLeaseCount": 0}, {"Id": 10575, "Pre": "Xã", "Name": "Thái Hưng", "UnsignedLoweredName": null, "FullAddress": null, "DistrictId": 593, "CityId": null, "ProductSellCount": 0, "ProductLeaseCount": 0}, {"Id": 10579, "Pre": "Xã", "Name": "Thái Nguyên", "UnsignedLoweredName": null, "FullAddress": null, "DistrictId": 593, "CityId": null, "ProductSellCount": 0, "ProductLeaseCount": 0}, {"Id": 10553, "Pre": "Xã", "Name": "Thái Phúc", "UnsignedLoweredName": null, "FullAddress": null, "DistrictId": 593, "CityId": null, "ProductSellCount": 0, "ProductLeaseCount": 0}, {"Id": 10550, "Pre": "Xã", "Name": "Thái Sơn", "UnsignedLoweredName": null, "FullAddress": null, "DistrictId": 593, "CityId": null, "ProductSellCount": 0, "ProductLeaseCount": 0}, {"Id": 10569, "Pre": "Xã", "Name": "Thái Tân", "UnsignedLoweredName": null, "FullAddress": null, "DistrictId": 593, "CityId": null, "ProductSellCount": 0, "ProductLeaseCount": 0}, {"Id": 10557, "Pre": "Xã", "Name": "Thái Thành", "UnsignedLoweredName": null, "FullAddress": null, "DistrictId": 593, "CityId": null, "ProductSellCount": 0, "ProductLeaseCount": 0}, {"Id": 10558, "Pre": "Xã", "Name": "Thái Thịnh", "UnsignedLoweredName": null, "FullAddress": null, "DistrictId": 593, "CityId": null, "ProductSellCount": 0, "ProductLeaseCount": 0}, {"Id": 10560, "Pre": "Xã", "Name": "Thái Thọ", "UnsignedLoweredName": null, "FullAddress": null, "DistrictId": 593, "CityId": null, "ProductSellCount": 0, "ProductLeaseCount": 0}, {"Id": 10556, "Pre": "Xã", "Name": "Thái Thuần", "UnsignedLoweredName": null, "FullAddress": null, "DistrictId": 593, "CityId": null, "ProductSellCount": 0, "ProductLeaseCount": 0}, {"Id": 10477, "Pre": "Xã", "Name": "Thái Thủy", "UnsignedLoweredName": null, "FullAddress": null, "DistrictId": 593, "CityId": null, "ProductSellCount": 0, "ProductLeaseCount": 0}, {"Id": 10482, "Pre": "Xã", "Name": "Thái Thượng", "UnsignedLoweredName": null, "FullAddress": null, "DistrictId": 593, "CityId": null, "ProductSellCount": 0, "ProductLeaseCount": 0}, {"Id": 10480, "Pre": "Xã", "Name": "Thái Xuyên", "UnsignedLoweredName": null, "FullAddress": null, "DistrictId": 593, "CityId": null, "ProductSellCount": 0, "ProductLeaseCount": 0}, {"Id": 10539, "Pre": "Xã", "Name": "Thụy An", "UnsignedLoweredName": null, "FullAddress": null, "DistrictId": 593, "CityId": null, "ProductSellCount": 0, "ProductLeaseCount": 0}, {"Id": 10501, "Pre": "Xã", "Name": "Thụy Bình", "UnsignedLoweredName": null, "FullAddress": null, "DistrictId": 593, "CityId": null, "ProductSellCount": 0, "ProductLeaseCount": 0}, {"Id": 10487, "Pre": "Xã", "Name": "Thụy Chính", "UnsignedLoweredName": null, "FullAddress": null, "DistrictId": 593, "CityId": null, "ProductSellCount": 0, "ProductLeaseCount": 0}, {"Id": 10489, "Pre": "Xã", "Name": "Thụy Dân", "UnsignedLoweredName": null, "FullAddress": null, "DistrictId": 593, "CityId": null, "ProductSellCount": 0, "ProductLeaseCount": 0}, {"Id": 10537, "Pre": "Xã", "Name": "Thụy Dũng", "UnsignedLoweredName": null, "FullAddress": null, "DistrictId": 593, "CityId": null, "ProductSellCount": 0, "ProductLeaseCount": 0}, {"Id": 10490, "Pre": "Xã", "Name": "Thụy Duyên", "UnsignedLoweredName": null, "FullAddress": null, "DistrictId": 593, "CityId": null, "ProductSellCount": 0, "ProductLeaseCount": 0}, {"Id": 10498, "Pre": "Xã", "Name": "Thụy Dương", "UnsignedLoweredName": null, "FullAddress": null, "DistrictId": 593, "CityId": null, "ProductSellCount": 0, "ProductLeaseCount": 0}, {"Id": 10504, "Pre": "Xã", "Name": "Thụy Hà", "UnsignedLoweredName": null, "FullAddress": null, "DistrictId": 593, "CityId": null, "ProductSellCount": 0, "ProductLeaseCount": 0}, {"Id": 10542, "Pre": "Xã", "Name": "Thụy Hải", "UnsignedLoweredName": null, "FullAddress": null, "DistrictId": 593, "CityId": null, "ProductSellCount": 0, "ProductLeaseCount": 0}, {"Id": 10530, "Pre": "Xã", "Name": "Thụy Hồng", "UnsignedLoweredName": null, "FullAddress": null, "DistrictId": 593, "CityId": null, "ProductSellCount": 0, "ProductLeaseCount": 0}, {"Id": 10496, "Pre": "Xã", "Name": "Thụy Hưng", "UnsignedLoweredName": null, "FullAddress": null, "DistrictId": 593, "CityId": null, "ProductSellCount": 0, "ProductLeaseCount": 0}, {"Id": 10503, "Pre": "Xã", "Name": "Thụy Liên", "UnsignedLoweredName": null, "FullAddress": null, "DistrictId": 593, "CityId": null, "ProductSellCount": 0, "ProductLeaseCount": 0}, {"Id": 10506, "Pre": "Xã", "Name": "Thụy Lương", "UnsignedLoweredName": null, "FullAddress": null, "DistrictId": 593, "CityId": null, "ProductSellCount": 0, "ProductLeaseCount": 0}, {"Id": 10475, "Pre": "Xã", "Name": "Thụy Ninh", "UnsignedLoweredName": null, "FullAddress": null, "DistrictId": 593, "CityId": null, "ProductSellCount": 0, "ProductLeaseCount": 0}, {"Id": 10493, "Pre": "Xã", "Name": "Thụy Phong", "UnsignedLoweredName": null, "FullAddress": null, "DistrictId": 593, "CityId": null, "ProductSellCount": 0, "ProductLeaseCount": 0}, {"Id": 10535, "Pre": "Xã", "Name": "Thụy Phúc", "UnsignedLoweredName": null, "FullAddress": null, "DistrictId": 593, "CityId": null, "ProductSellCount": 0, "ProductLeaseCount": 0}, {"Id": 10508, "Pre": "Xã", "Name": "Thụy Quỳnh", "UnsignedLoweredName": null, "FullAddress": null, "DistrictId": 593, "CityId": null, "ProductSellCount": 0, "ProductLeaseCount": 0}, {"Id": 10494, "Pre": "Xã", "Name": "Thụy Sơn", "UnsignedLoweredName": null, "FullAddress": null, "DistrictId": 593, "CityId": null, "ProductSellCount": 0, "ProductLeaseCount": 0}, {"Id": 10538, "Pre": "Xã", "Name": "Thụy Tân", "UnsignedLoweredName": null, "FullAddress": null, "DistrictId": 593, "CityId": null, "ProductSellCount": 0, "ProductLeaseCount": 0}, {"Id": 10491, "Pre": "Xã", "Name": "Thụy Thanh", "UnsignedLoweredName": null, "FullAddress": null, "DistrictId": 593, "CityId": null, "ProductSellCount": 0, "ProductLeaseCount": 0}, {"Id": 10509, "Pre": "Xã", "Name": "Thụy Trình", "UnsignedLoweredName": null, "FullAddress": null, "DistrictId": 593, "CityId": null, "ProductSellCount": 0, "ProductLeaseCount": 0}, {"Id": 10546, "Pre": "Xã", "Name": "Thụy Trường", "UnsignedLoweredName": null, "FullAddress": null, "DistrictId": 593, "CityId": null, "ProductSellCount": 0, "ProductLeaseCount": 0}, {"Id": 10499, "Pre": "Xã", "Name": "Thụy Văn", "UnsignedLoweredName": null, "FullAddress": null, "DistrictId": 593, "CityId": null, "ProductSellCount": 0, "ProductLeaseCount": 0}, {"Id": 10497, "Pre": "Xã", "Name": "Thụy Việt", "UnsignedLoweredName": null, "FullAddress": null, "DistrictId": 593, "CityId": null, "ProductSellCount": 0, "ProductLeaseCount": 0}, {"Id": 10544, "Pre": "Xã", "Name": "Thụy Xuân", "UnsignedLoweredName": null, "FullAddress": null, "DistrictId": 593, "CityId": null, "ProductSellCount": 0, "ProductLeaseCount": 0}], "Streets": [{"Id": 18845, "Pre": "Phố", "Name": "37", "UnsignedLoweredName": null, "FullAddress": null, "DistrictId": 593, "CityId": null, "ProductSellCount": 0, "ProductLeaseCount": 0}, {"Id": 18846, "Pre": "Đường", "Name": "39", "UnsignedLoweredName": null, "FullAddress": null, "DistrictId": 593, "CityId": null, "ProductSellCount": 0, "ProductLeaseCount": 0}, {"Id": 18847, "Pre": "Đường", "Name": "47", "UnsignedLoweredName": null, "FullAddress": null, "DistrictId": 593, "CityId": null, "ProductSellCount": 0, "ProductLeaseCount": 0}, {"Id": 18848, "Pre": "Đường", "Name": "Tỉnh lộ 216", "UnsignedLoweredName": null, "FullAddress": null, "DistrictId": 593, "CityId": null, "ProductSellCount": 0, "ProductLeaseCount": 0}, {"Id": 18849, "Pre": "Đường", "Name": "Tỉnh lộ 39B", "UnsignedLoweredName": null, "FullAddress": null, "DistrictId": 593, "CityId": null, "ProductSellCount": 0, "ProductLeaseCount": 0}, {"Id": 4316, "Pre": "Đường", "Name": "Tỉnh lộ 460", "UnsignedLoweredName": null, "FullAddress": null, "DistrictId": 593, "CityId": null, "ProductSellCount": 0, "ProductLeaseCount": 0}], "Area": null, "Population": null, "PopulationDensity": null, "ImagesJson": null, "Url": null}, {"Id": 595, "Pre": "Huyện", "Name": "Vũ Thư", "UnsignedLoweredName": null, "CityId": 54, "FullAddress": null, "Latitude": null, "Longitude": null, "Polygon": null, "ProductSellCount": 0, "ProductLeaseCount": 0, "Wards": [{"Id": 10719, "Pre": "Xã", "Name": "Bách Thuận", "UnsignedLoweredName": null, "FullAddress": null, "DistrictId": 595, "CityId": null, "ProductSellCount": 0, "ProductLeaseCount": 0}, {"Id": 10720, "Pre": "Xã", "Name": "Dũng Nghĩa", "UnsignedLoweredName": null, "FullAddress": null, "DistrictId": 595, "CityId": null, "ProductSellCount": 0, "ProductLeaseCount": 0}, {"Id": 10706, "Pre": "Xã", "Name": "Duy Nhất", "UnsignedLoweredName": null, "FullAddress": null, "DistrictId": 595, "CityId": null, "ProductSellCount": 0, "ProductLeaseCount": 0}, {"Id": 10709, "Pre": "Xã", "Name": "Đồng Thanh", "UnsignedLoweredName": null, "FullAddress": null, "DistrictId": 595, "CityId": null, "ProductSellCount": 0, "ProductLeaseCount": 0}, {"Id": 10693, "Pre": "Xã", "Name": "Hiệp Hòa", "UnsignedLoweredName": null, "FullAddress": null, "DistrictId": 595, "CityId": null, "ProductSellCount": 0, "ProductLeaseCount": 0}, {"Id": 10724, "Pre": "Xã", "Name": "Hòa Bình", "UnsignedLoweredName": null, "FullAddress": null, "DistrictId": 595, "CityId": null, "ProductSellCount": 0, "ProductLeaseCount": 0}, {"Id": 10727, "Pre": "Xã", "Name": "Hồng Lý", "UnsignedLoweredName": null, "FullAddress": null, "DistrictId": 595, "CityId": null, "ProductSellCount": 0, "ProductLeaseCount": 0}, {"Id": 10701, "Pre": "Xã", "Name": "Hồng Phong", "UnsignedLoweredName": null, "FullAddress": null, "DistrictId": 595, "CityId": null, "ProductSellCount": 0, "ProductLeaseCount": 0}, {"Id": 10722, "Pre": "Xã", "Name": "Minh Khai", "UnsignedLoweredName": null, "FullAddress": null, "DistrictId": 595, "CityId": null, "ProductSellCount": 0, "ProductLeaseCount": 0}, {"Id": 10686, "Pre": "Xã", "Name": "Minh Lãng", "UnsignedLoweredName": null, "FullAddress": null, "DistrictId": 595, "CityId": null, "ProductSellCount": 0, "ProductLeaseCount": 0}, {"Id": 10705, "Pre": "Xã", "Name": "Minh Quang", "UnsignedLoweredName": null, "FullAddress": null, "DistrictId": 595, "CityId": null, "ProductSellCount": 0, "ProductLeaseCount": 0}, {"Id": 10710, "Pre": "Xã", "Name": "Nguyên Xá", "UnsignedLoweredName": null, "FullAddress": null, "DistrictId": 595, "CityId": null, "ProductSellCount": 0, "ProductLeaseCount": 0}, {"Id": 10708, "Pre": "Xã", "Name": "Phúc Thành", "UnsignedLoweredName": null, "FullAddress": null, "DistrictId": 595, "CityId": null, "ProductSellCount": 0, "ProductLeaseCount": 0}, {"Id": 10684, "Pre": "Xã", "Name": "Song An", "UnsignedLoweredName": null, "FullAddress": null, "DistrictId": 595, "CityId": null, "ProductSellCount": 0, "ProductLeaseCount": 0}, {"Id": 10685, "Pre": "Xã", "Name": "Song Lãng", "UnsignedLoweredName": null, "FullAddress": null, "DistrictId": 595, "CityId": null, "ProductSellCount": 0, "ProductLeaseCount": 0}, {"Id": 10702, "Pre": "Xã", "Name": "Tam Quang", "UnsignedLoweredName": null, "FullAddress": null, "DistrictId": 595, "CityId": null, "ProductSellCount": 0, "ProductLeaseCount": 0}, {"Id": 10694, "Pre": "Xã", "Name": "Tân Hòa", "UnsignedLoweredName": null, "FullAddress": null, "DistrictId": 595, "CityId": null, "ProductSellCount": 0, "ProductLeaseCount": 0}, {"Id": 10696, "Pre": "Xã", "Name": "Tân Lập", "UnsignedLoweredName": null, "FullAddress": null, "DistrictId": 595, "CityId": null, "ProductSellCount": 0, "ProductLeaseCount": 0}, {"Id": 10699, "Pre": "Xã", "Name": "Tân Phong", "UnsignedLoweredName": null, "FullAddress": null, "DistrictId": 595, "CityId": null, "ProductSellCount": 0, "ProductLeaseCount": 0}, {"Id": 10707, "Pre": "Xã", "Name": "Tự Tân", "UnsignedLoweredName": null, "FullAddress": null, "DistrictId": 595, "CityId": null, "ProductSellCount": 0, "ProductLeaseCount": 0}, {"Id": 10683, "Pre": "Xã", "Name": "Trung An", "UnsignedLoweredName": null, "FullAddress": null, "DistrictId": 595, "CityId": null, "ProductSellCount": 0, "ProductLeaseCount": 0}, {"Id": 10713, "Pre": "Xã", "Name": "Việt Hùng", "UnsignedLoweredName": null, "FullAddress": null, "DistrictId": 595, "CityId": null, "ProductSellCount": 0, "ProductLeaseCount": 0}, {"Id": 10715, "Pre": "Xã", "Name": "Việt Thuận", "UnsignedLoweredName": null, "FullAddress": null, "DistrictId": 595, "CityId": null, "ProductSellCount": 0, "ProductLeaseCount": 0}, {"Id": 10690, "Pre": "Xã", "Name": "Vũ Đoài", "UnsignedLoweredName": null, "FullAddress": null, "DistrictId": 595, "CityId": null, "ProductSellCount": 0, "ProductLeaseCount": 0}, {"Id": 10689, "Pre": "Xã", "Name": "Vũ Hội", "UnsignedLoweredName": null, "FullAddress": null, "DistrictId": 595, "CityId": null, "ProductSellCount": 0, "ProductLeaseCount": 0}, {"Id": 10691, "Pre": "Xã", "Name": "Vũ Tiến", "UnsignedLoweredName": null, "FullAddress": null, "DistrictId": 595, "CityId": null, "ProductSellCount": 0, "ProductLeaseCount": 0}, {"Id": 10679, "Pre": "Thị trấn", "Name": "Vũ Thư", "UnsignedLoweredName": null, "FullAddress": null, "DistrictId": 595, "CityId": null, "ProductSellCount": 0, "ProductLeaseCount": 0}, {"Id": 10687, "Pre": "Xã", "Name": "Vũ Vân", "UnsignedLoweredName": null, "FullAddress": null, "DistrictId": 595, "CityId": null, "ProductSellCount": 0, "ProductLeaseCount": 0}, {"Id": 10688, "Pre": "Xã", "Name": "Vũ Vinh", "UnsignedLoweredName": null, "FullAddress": null, "DistrictId": 595, "CityId": null, "ProductSellCount": 0, "ProductLeaseCount": 0}, {"Id": 10692, "Pre": "Xã", "Name": "Xuân Hòa", "UnsignedLoweredName": null, "FullAddress": null, "DistrictId": 595, "CityId": null, "ProductSellCount": 0, "ProductLeaseCount": 0}], "Streets": [{"Id": 18853, "Pre": "Đường", "Name": "10", "UnsignedLoweredName": null, "FullAddress": null, "DistrictId": 595, "CityId": null, "ProductSellCount": 0, "ProductLeaseCount": 0}, {"Id": 18854, "Pre": "Đường", "Name": "39", "UnsignedLoweredName": null, "FullAddress": null, "DistrictId": 595, "CityId": null, "ProductSellCount": 0, "ProductLeaseCount": 0}, {"Id": 4346, "Pre": "Đường", "Name": "LH 23", "UnsignedLoweredName": null, "FullAddress": null, "DistrictId": 595, "CityId": null, "ProductSellCount": 0, "ProductLeaseCount": 0}, {"Id": 8223, "Pre": "Đường", "Name": "Minh Quang", "UnsignedLoweredName": null, "FullAddress": null, "DistrictId": 595, "CityId": null, "ProductSellCount": 0, "ProductLeaseCount": 0}, {"Id": 18855, "Pre": "Đường", "Name": "Quốc Lộ 10", "UnsignedLoweredName": null, "FullAddress": null, "DistrictId": 595, "CityId": null, "ProductSellCount": 0, "ProductLeaseCount": 0}, {"Id": 18856, "Pre": "Đường", "Name": "Tỉnh lộ 223", "UnsignedLoweredName": null, "FullAddress": null, "DistrictId": 595, "CityId": null, "ProductSellCount": 0, "ProductLeaseCount": 0}, {"Id": 4345, "Pre": "Đường", "Name": "Tỉnh lộ 454", "UnsignedLoweredName": null, "FullAddress": null, "DistrictId": 595, "CityId": null, "ProductSellCount": 0, "ProductLeaseCount": 0}, {"Id": 4344, "Pre": "Đường", "Name": "Tỉnh lộ 463", "UnsignedLoweredName": null, "FullAddress": null, "DistrictId": 595, "CityId": null, "ProductSellCount": 0, "ProductLeaseCount": 0}], "Area": null, "Population": null, "PopulationDensity": null, "ImagesJson": null, "Url": null}]}